odoo/addons/pos_financial_risk/README.rst
odoo/addons/pos_financial_risk/__init__.py
odoo/addons/pos_financial_risk/__manifest__.py
odoo/addons/pos_financial_risk/i18n/es.po
odoo/addons/pos_financial_risk/i18n/it.po
odoo/addons/pos_financial_risk/i18n/pos_financial_risk.pot
odoo/addons/pos_financial_risk/models/__init__.py
odoo/addons/pos_financial_risk/models/pos_config.py
odoo/addons/pos_financial_risk/models/pos_payment_method.py
odoo/addons/pos_financial_risk/models/pos_session.py
odoo/addons/pos_financial_risk/models/res_config_settings.py
odoo/addons/pos_financial_risk/readme/CONFIGURE.rst
odoo/addons/pos_financial_risk/readme/CONTRIBUTORS.rst
odoo/addons/pos_financial_risk/readme/DESCRIPTION.rst
odoo/addons/pos_financial_risk/readme/USAGE.rst
odoo/addons/pos_financial_risk/static/description/icon.png
odoo/addons/pos_financial_risk/static/description/index.html
odoo/addons/pos_financial_risk/static/src/js/PaymentScreen.esm.js
odoo/addons/pos_financial_risk/static/src/scss/pos.scss
odoo/addons/pos_financial_risk/static/src/xml/PaymentScreen.xml
odoo/addons/pos_financial_risk/views/pos_payment_method_views.xml
odoo/addons/pos_financial_risk/views/res_config_settings_views.xml
odoo_addon_pos_financial_risk-16.0.1.0.1.3.dist-info/METADATA
odoo_addon_pos_financial_risk-16.0.1.0.1.3.dist-info/WHEEL
odoo_addon_pos_financial_risk-16.0.1.0.1.3.dist-info/top_level.txt
odoo_addon_pos_financial_risk-16.0.1.0.1.3.dist-info/RECORD
